Changelog
MANIFEST.in
README.rst
logex.py
setup.cfg
setup.py
examples/advanced.py
examples/cross_module.py
examples/cross_module2.py
examples/dbus_method.py
examples/dbus_signal.py
examples/excepthook.py
examples/nested.py
examples/simple.py
examples/thread_function.py
logex.egg-info/PKG-INFO
logex.egg-info/SOURCES.txt
logex.egg-info/dependency_links.txt
logex.egg-info/top_level.txt